prompt_bottle-0.4.1.dist-info/METADATA
prompt_bottle-0.4.1.dist-info/WHEEL
prompt_bottle-0.4.1.dist-info/entry_points.txt
prompt_bottle/__init__.py
prompt_bottle/parse.py
prompt_bottle/pipeline.py
prompt_bottle/pydantic_ai_utils.py
prompt_bottle-0.4.1.dist-info/RECORD
