Metadata-Version: 2.1
Name: prompt_bottle
Version: 0.4.1
Summary: Prompt template engine, built upon Jinja
Author-Email: Yanli <mail@yanli.one>
License: MIT
Project-URL: Repository, https://github.com/BeautyyuYanli/Prompt-Bottle
Requires-Python: >=3.10
Requires-Dist: minijinja>=2.11.0
Requires-Dist: pydantic-ai-slim>=1.0.2
Requires-Dist: StrEnum>=0.4.15; python_version < "3.11"
